<annotation>
	<image>2008_002430</image>
	<voc_id>2</voc_id>
	<category>sheep</category>
	<visible_bounds height="198.00" width="78.00" xmin="418.00" ymin="60.00" />
	<keypoints>
		<keypoint name="L_Eye" visible="1" x="455.93" y="72.71" z="0.00" />
		<keypoint name="R_Eye" visible="1" x="430.21" y="72.71" z="0.00" />
		<keypoint name="Nose" visible="1" x="436.50" y="88.01" z="0.00" />
		<keypoint name="L_EarBase" visible="1" x="463.00" y="74.08" z="0.00" />
		<keypoint name="R_EarBase" visible="1" x="430.41" y="74.87" z="0.00" />
		<keypoint name="Throat" visible="1" x="438.95" y="115.46" z="0.00" />
		<keypoint name="L_F_Elbow" visible="1" x="466.73" y="179.79" z="0.00" />
		<keypoint name="R_F_Elbow" visible="1" x="422.76" y="170.57" z="0.00" />
		<keypoint name="L_B_Elbow" visible="1" x="484.00" y="187.83" z="0.00" />
		<keypoint name="L_F_Paw" visible="1" x="466.04" y="251.66" z="0.00" />
		<keypoint name="R_F_Paw" visible="1" x="432.57" y="226.66" z="0.00" />
		<keypoint name="L_B_Paw" visible="1" x="496.96" y="236.66" z="0.00" />
		<keypoint name="R_B_Paw" visible="1" x="457.21" y="243.72" z="0.00" />
	<keypoint name="Withers" visible="0" x="0.00" y="0.00" z="0.00" /><keypoint name="TailBase" visible="0" x="0.00" y="0.00" z="0.00" /><keypoint name="R_B_Elbow" visible="0" x="0.00" y="0.00" z="0.00" /><keypoint name="L_F_Knee" visible="1" x="463.75" y="223.86000061035156" z="0.00" /><keypoint name="R_F_Knee" visible="1" x="426.25" y="189.4199981689453" z="0.00" /><keypoint name="L_B_Knee" visible="1" x="493.125" y="228.77999877929688" z="0.00" /><keypoint name="R_B_Knee" visible="1" x="450.0" y="224.27000427246094" z="0.00" /></keypoints>
	<polylinesegments>
		<segment name="foreground" x="440.42 435.12 428.06 427.47 420.40 425.11 430.41 427.47 431.00 431.00 428.06 419.81 416.28 419.22 418.63 424.52 427.47 428.06 428.64 441.60 442.19 436.30 433.94 444.54 448.67 450.43 452.79 461.03 462.80 470.46 472.22 468.69 471.04 470.46 476.93 483.41 484.59 484.59 488.71 493.42 496.37 491.66 493.42 489.30 491.66 494.01 486.94 481.64 479.88 472.81 461.03 454.56 456.91 459.86 468.69 471.63 476.34 468.69 462.21 459.86 458.68 452.79 445.72 " y="60.16 63.69 64.87 68.98 70.75 77.22 79.57 91.93 103.11 114.29 125.46 137.23 153.70 173.12 187.24 197.24 213.13 233.72 235.48 232.54 224.31 211.36 196.65 205.48 220.78 237.25 249.02 247.84 255.49 258.43 250.19 234.90 223.13 214.30 213.72 201.95 219.01 230.19 241.96 243.72 229.60 211.36 203.71 193.71 176.65 154.88 143.11 136.64 126.05 115.46 111.93 111.93 99.58 89.58 85.46 76.04 71.34 68.98 68.98 67.81 63.10 63.10 60.16 " />
	</polylinesegments>
</annotation>