<annotation>
	<image>2008_000721</image>
	<voc_id>1</voc_id>
	<category>dog</category>
	<visible_bounds height="371.00" width="434.00" xmin="62.00" ymin="4.00" />
	<keypoints>
		<keypoint name="L_Eye" visible="1" x="326.95" y="74.57" z="0.00" />
		<keypoint name="Nose" visible="1" x="201.11" y="103.51" z="0.00" />
		<keypoint name="L_EarBase" visible="1" x="368.28" y="63.83" z="0.00" />
		<keypoint name="Throat" visible="1" x="282.31" y="349.72" z="0.00" />
	<keypoint name="R_Eye" visible="0" x="0.00" y="0.00" z="0.00" /><keypoint name="R_EarBase" visible="0" x="0.00" y="0.00" z="0.00" /><keypoint name="L_F_Elbow" visible="0" x="0.00" y="0.00" z="0.00" /><keypoint name="R_F_Elbow" visible="0" x="0.00" y="0.00" z="0.00" /><keypoint name="L_F_Paw" visible="0" x="0.00" y="0.00" z="0.00" /><keypoint name="R_F_Paw" visible="0" x="0.00" y="0.00" z="0.00" /><keypoint name="Withers" visible="0" x="0.00" y="0.00" z="0.00" /><keypoint name="TailBase" visible="0" x="0.00" y="0.00" z="0.00" /><keypoint name="L_B_Paw" visible="0" x="0.00" y="0.00" z="0.00" /><keypoint name="R_B_Paw" visible="0" x="0.00" y="0.00" z="0.00" /><keypoint name="L_B_Elbow" visible="0" x="0.00" y="0.00" z="0.00" /><keypoint name="R_B_Elbow" visible="0" x="0.00" y="0.00" z="0.00" /><keypoint name="L_F_Knee" visible="0" x="0.00" y="0.00" z="0.00" /><keypoint name="R_F_Knee" visible="0" x="0.00" y="0.00" z="0.00" /><keypoint name="L_B_Knee" visible="0" x="0.00" y="0.00" z="0.00" /><keypoint name="R_B_Knee" visible="0" x="0.00" y="0.00" z="0.00" /></keypoints>
	<polylinesegments>
		<segment name="foreground" x="164.37 215.07 251.44 284.51 333.01 390.32 453.15 488.42 484.01 393.63 400.24 193.03 164.37 134.61 85.01 88.32 113.67 115.87 113.67 140.12 141.22 144.53 " y="40.68 15.32 19.73 7.60 27.45 90.28 163.04 246.82 285.41 285.41 369.19 376.91 349.35 369.19 374.70 311.87 275.49 243.52 189.50 165.25 115.64 78.16 " />
	</polylinesegments>
</annotation>