<annotation>
	<image>2009_004425</image>
	<voc_id>1</voc_id>
	<category>dog</category>
	<visible_bounds height="147.00" width="230.00" xmin="249.00" ymin="50.00" />
	<keypoints>
		<keypoint name="L_Eye" visible="1" x="267.26" y="142.33" z="0.00" />
		<keypoint name="R_Eye" visible="1" x="253.70" y="137.29" z="0.00" />
		<keypoint name="Nose" visible="1" x="254.37" y="160.00" z="0.00" />
		<keypoint name="L_EarBase" visible="1" x="282.27" y="126.79" z="0.00" />
		<keypoint name="R_EarBase" visible="1" x="257.69" y="119.48" z="0.00" />
		<keypoint name="Throat" visible="1" x="299.68" y="136.93" z="0.00" />
		<keypoint name="Withers" visible="1" x="298.62" y="91.32" z="0.00" />
		<keypoint name="TailBase" visible="1" x="432.04" y="63.42" z="0.00" />
		<keypoint name="L_F_Elbow" visible="1" x="354.61" y="133.03" z="0.00" />
		<keypoint name="L_B_Elbow" visible="1" x="402.54" y="101.95" z="0.00" />
		<keypoint name="R_B_Elbow" visible="1" x="433.63" y="127.99" z="0.00" />
		<keypoint name="L_F_Paw" visible="1" x="328.52" y="178.34" z="0.00" />
		<keypoint name="R_F_Paw" visible="1" x="294.37" y="189.50" z="0.00" />
		<keypoint name="L_B_Paw" visible="1" x="389.34" y="180.86" z="0.00" />
		<keypoint name="R_B_Paw" visible="1" x="432.70" y="157.35" z="0.00" />
	<keypoint name="R_F_Elbow" visible="0" x="0.00" y="0.00" z="0.00" /><keypoint name="L_F_Knee" visible="1" x="320.625" y="164.0625" z="0.00" /><keypoint name="R_F_Knee" visible="1" x="306.25" y="166.40625" z="0.00" /><keypoint name="L_B_Knee" visible="1" x="410.0" y="160.78125" z="0.00" /><keypoint name="R_B_Knee" visible="1" x="433.125" y="133.59375" z="0.00" /></keypoints>
	<polylinesegments>
		<segment name="foreground" x="258.75 325.73 402.80 434.17 464.46 480.41 475.63 460.74 440.54 441.08 430.98 441.08 428.85 422.47 418.75 418.22 396.42 380.48 375.69 381.54 392.70 401.21 399.08 395.36 394.83 394.83 391.11 359.75 329.98 337.95 324.66 315.10 305.53 282.14 282.67 300.74 308.72 300.21 287.99 258.22 249.72 249.18 " y="105.93 66.61 48.54 57.57 48.01 51.19 66.61 68.20 73.51 102.74 119.75 162.26 164.92 136.75 144.73 161.20 187.77 187.77 181.93 176.61 176.08 162.79 146.32 134.63 113.37 105.93 105.93 128.25 169.17 179.27 186.18 176.61 192.02 195.74 185.11 173.42 145.79 143.13 152.17 169.17 166.51 116.03 " />
	</polylinesegments>
</annotation>