<annotation>
	<image>2009_003768</image>
	<voc_id>1</voc_id>
	<category>horse</category>
	<visible_bounds height="268.00" width="304.00" xmin="20.00" ymin="158.00" />
	<keypoints>
		<keypoint name="R_Eye" visible="1" x="292.92" y="178.52" z="0.00" />
		<keypoint name="Nose" visible="1" x="319.58" y="190.86" z="0.00" />
		<keypoint name="R_EarBase" visible="1" x="271.44" y="173.74" z="0.00" />
		<keypoint name="Throat" visible="1" x="283.38" y="239.71" z="0.00" />
		<keypoint name="Withers" visible="1" x="235.25" y="221.52" z="0.00" />
		<keypoint name="TailBase" visible="1" x="73.88" y="252.45" z="0.00" />
		<keypoint name="R_F_Elbow" visible="1" x="253.54" y="306.33" z="0.00" />
		<keypoint name="R_B_Elbow" visible="1" x="110.74" y="306.60" z="0.00" />
		<keypoint name="L_F_Paw" visible="1" x="219.73" y="398.98" z="0.00" />
		<keypoint name="R_F_Paw" visible="1" x="259.51" y="400.30" z="0.00" />
		<keypoint name="L_B_Paw" visible="1" x="33.18" y="414.24" z="0.00" />
		<keypoint name="R_B_Paw" visible="1" x="123.07" y="411.05" z="0.00" />
	<keypoint name="L_Eye" visible="0" x="0.00" y="0.00" z="0.00" /><keypoint name="L_EarBase" visible="0" x="0.00" y="0.00" z="0.00" /><keypoint name="L_F_Elbow" visible="0" x="0.00" y="0.00" z="0.00" /><keypoint name="L_B_Elbow" visible="0" x="0.00" y="0.00" z="0.00" /><keypoint name="L_F_Knee" visible="1" x="225.86874389648438" y="356.875" z="0.00" /><keypoint name="R_F_Knee" visible="1" x="282.2250061035156" y="343.75" z="0.00" /><keypoint name="L_B_Knee" visible="1" x="55.46875" y="349.375" z="0.00" /><keypoint name="R_B_Knee" visible="1" x="101.6187515258789" y="365.0" z="0.00" /></keypoints>
	<polylinesegments>
		<segment name="foreground" x="157.68 238.03 242.80 248.37 262.69 274.63 274.63 304.06 323.16 321.56 286.56 285.76 279.40 281.79 268.26 286.56 287.36 282.58 266.67 256.33 249.17 253.15 266.67 272.24 242.80 237.24 230.08 227.69 230.08 238.83 210.98 207.00 217.35 218.94 154.50 129.84 131.43 109.15 105.97 130.63 113.92 103.58 91.65 85.28 94.83 74.15 63.01 48.69 42.32 31.19 20.05 24.03 38.35 36.76 39.94 63.80 74.15 109.15 141.77 " y="237.05 228.29 184.49 160.60 158.21 156.62 166.18 170.96 187.68 206.79 214.75 256.16 273.68 293.59 309.52 342.17 354.91 375.62 405.08 405.88 395.52 382.78 366.06 345.35 323.85 346.95 373.23 385.17 393.93 404.28 413.84 403.49 366.86 326.24 309.52 290.41 308.72 364.47 373.23 408.27 418.62 414.64 373.23 361.28 327.84 346.95 358.89 397.12 415.43 419.41 407.47 389.95 369.25 309.52 273.68 249.00 249.00 233.07 234.66 " />
	</polylinesegments>
</annotation>