<annotation>
	<image>2010_005929</image>
	<voc_id>1</voc_id>
	<category>dog</category>
	<visible_bounds height="242.00" width="245.00" xmin="62.00" ymin="31.00" />
	<keypoints>
		<keypoint name="L_Eye" visible="1" x="116.06" y="125.21" z="0.00" />
		<keypoint name="R_Eye" visible="1" x="73.94" y="107.42" z="0.00" />
		<keypoint name="Nose" visible="1" x="85.64" y="134.56" z="0.00" />
		<keypoint name="L_EarBase" visible="1" x="154.40" y="88.00" z="0.00" />
		<keypoint name="R_EarBase" visible="1" x="73.58" y="67.15" z="0.00" />
		<keypoint name="Throat" visible="1" x="98.84" y="168.54" z="0.00" />
		<keypoint name="Withers" visible="1" x="172.28" y="111.97" z="0.00" />
		<keypoint name="TailBase" visible="1" x="269.96" y="100.23" z="0.00" />
		<keypoint name="L_F_Elbow" visible="1" x="137.48" y="199.10" z="0.00" />
		<keypoint name="R_F_Elbow" visible="1" x="120.92" y="171.42" z="0.00" />
		<keypoint name="L_B_Elbow" visible="1" x="259.88" y="149.12" z="0.00" />
		<keypoint name="R_B_Elbow" visible="1" x="239.00" y="137.62" z="0.00" />
		<keypoint name="L_F_Paw" visible="1" x="102.68" y="267.29" z="0.00" />
		<keypoint name="R_F_Paw" visible="1" x="112.52" y="238.29" z="0.00" />
		<keypoint name="L_B_Paw" visible="1" x="248.36" y="237.57" z="0.00" />
		<keypoint name="R_B_Paw" visible="1" x="209.66" y="195.68" z="0.00" />
	<keypoint name="L_F_Knee" visible="1" x="123.63999938964844" y="241.92001342773438" z="0.00" /><keypoint name="R_F_Knee" visible="0" x="0.00" y="0.00" z="0.00" /><keypoint name="L_B_Knee" visible="1" x="268.3999938964844" y="203.04000854492188" z="0.00" /><keypoint name="R_B_Knee" visible="1" x="235.39999389648438" y="183.9600067138672" z="0.00" /></keypoints>
	<polylinesegments>
		<segment name="foreground" x="79.16 92.12 116.60 135.32 167.72 179.24 175.64 182.84 196.52 231.08 249.80 269.96 285.80 290.12 285.80 274.28 259.16 283.64 296.60 301.64 308.12 303.08 282.92 290.84 281.48 274.28 271.40 279.32 262.04 260.60 241.16 236.84 237.56 246.20 257.72 247.64 231.08 215.96 197.96 200.12 213.08 228.92 229.64 223.88 205.16 190.04 169.16 164.84 155.48 145.40 125.24 118.04 102.20 90.68 98.60 107.96 107.24 113.72 123.08 123.08 93.56 92.84 100.04 85.64 66.20 66.20 63.32 63.32 61.16 69.08 " y="37.67 62.83 69.31 77.22 64.27 67.87 85.13 87.28 93.03 88.72 87.28 90.16 83.69 70.02 59.24 53.49 51.33 29.76 34.07 47.73 73.62 94.47 113.17 128.99 146.97 164.94 180.04 202.34 231.82 240.45 247.64 236.85 226.07 222.47 207.37 187.24 199.46 205.21 200.18 190.83 188.67 185.80 175.73 164.22 177.17 192.99 198.74 198.74 209.53 223.19 257.71 269.21 273.53 269.21 256.99 250.51 237.57 229.66 219.59 206.65 202.34 182.20 174.29 160.63 143.37 124.67 107.42 89.44 58.52 33.35 " />
	</polylinesegments>
</annotation>