<annotation>
	<image>2010_004362</image>
	<voc_id>1</voc_id>
	<category>dog</category>
	<visible_bounds height="269.00" width="255.00" xmin="148.00" ymin="69.00" />
	<keypoints>
		<keypoint name="L_Eye" visible="1" x="231.20" y="81.52" z="0.00" />
		<keypoint name="R_Eye" visible="1" x="191.68" y="82.16" z="0.00" />
		<keypoint name="Nose" visible="1" x="210.00" y="83.40" z="0.00" />
		<keypoint name="L_EarBase" visible="1" x="247.20" y="87.60" z="0.00" />
		<keypoint name="R_EarBase" visible="1" x="175.68" y="87.44" z="0.00" />
		<keypoint name="Throat" visible="1" x="201.60" y="148.35" z="0.00" />
		<keypoint name="Withers" visible="1" x="264.00" y="132.09" z="0.00" />
		<keypoint name="TailBase" visible="1" x="384.40" y="140.15" z="0.00" />
		<keypoint name="L_F_Elbow" visible="1" x="257.87" y="219.49" z="0.00" />
		<keypoint name="R_F_Elbow" visible="1" x="234.67" y="225.35" z="0.00" />
		<keypoint name="L_B_Elbow" visible="1" x="365.33" y="180.05" z="0.00" />
		<keypoint name="L_F_Paw" visible="1" x="244.80" y="326.11" z="0.00" />
		<keypoint name="R_F_Paw" visible="1" x="219.84" y="274.80" z="0.00" />
		<keypoint name="L_B_Paw" visible="1" x="352.32" y="297.82" z="0.00" />
		<keypoint name="R_B_Paw" visible="1" x="328.16" y="244.11" z="0.00" />
	<keypoint name="R_B_Elbow" visible="0" x="0.00" y="0.00" z="0.00" /><keypoint name="L_F_Knee" visible="1" x="257.5" y="274.21875" z="0.00" /><keypoint name="R_F_Knee" visible="1" x="234.375" y="243.28125" z="0.00" /><keypoint name="L_B_Knee" visible="1" x="371.875" y="257.8125" z="0.00" /><keypoint name="R_B_Knee" visible="0" x="0.00" y="0.00" z="0.00" /></keypoints>
	<polylinesegments>
		<segment name="foreground" x="149.60 173.60 182.40 184.00 194.40 229.60 240.00 261.60 276.80 262.40 248.80 248.00 256.00 249.60 271.20 344.00 383.20 375.20 336.80 346.40 393.60 406.40 392.80 392.00 392.80 375.20 373.60 384.80 372.00 366.40 362.40 344.00 339.20 354.40 360.80 346.40 332.80 316.80 324.00 335.20 339.20 331.20 332.00 326.40 296.00 273.60 274.40 265.60 260.00 256.00 225.60 224.00 241.60 245.60 238.40 216.00 203.20 224.00 225.60 201.60 191.20 180.00 185.60 179.20 166.40 157.60 " y="75.61 71.61 72.41 79.61 70.81 68.42 72.41 74.01 91.60 101.99 101.99 109.18 121.97 128.36 129.16 117.97 130.76 120.37 99.59 94.79 117.97 137.96 153.94 169.13 183.52 210.69 233.87 253.06 279.43 295.42 309.01 308.21 291.42 285.83 265.85 241.07 253.06 242.67 231.48 236.27 229.08 218.69 206.70 203.50 227.48 232.28 249.86 293.82 327.39 336.99 337.78 324.20 315.40 254.66 281.03 288.23 273.84 264.25 222.68 205.90 171.53 142.75 124.37 108.38 104.39 95.59 " />
	</polylinesegments>
</annotation>