<annotation>
	<image>2010_001829</image>
	<voc_id>2</voc_id>
	<category>horse</category>
	<visible_bounds height="290.00" width="275.00" xmin="183.00" ymin="43.00" />
	<keypoints>
		<keypoint name="L_Eye" visible="1" x="437.23" y="150.26" z="0.00" />
		<keypoint name="R_Eye" visible="1" x="365.32" y="148.36" z="0.00" />
		<keypoint name="Nose" visible="1" x="425.76" y="256.08" z="0.00" />
		<keypoint name="L_EarBase" visible="1" x="443.65" y="82.22" z="0.00" />
		<keypoint name="R_EarBase" visible="1" x="359.23" y="81.15" z="0.00" />
		<keypoint name="Throat" visible="1" x="370.15" y="275.32" z="0.00" />
		<keypoint name="Withers" visible="1" x="302.89" y="176.37" z="0.00" />
	<keypoint name="L_F_Elbow" visible="0" x="0.00" y="0.00" z="0.00" /><keypoint name="R_F_Elbow" visible="0" x="0.00" y="0.00" z="0.00" /><keypoint name="L_F_Paw" visible="0" x="0.00" y="0.00" z="0.00" /><keypoint name="R_F_Paw" visible="0" x="0.00" y="0.00" z="0.00" /><keypoint name="TailBase" visible="0" x="0.00" y="0.00" z="0.00" /><keypoint name="L_B_Paw" visible="0" x="0.00" y="0.00" z="0.00" /><keypoint name="R_B_Paw" visible="0" x="0.00" y="0.00" z="0.00" /><keypoint name="L_B_Elbow" visible="0" x="0.00" y="0.00" z="0.00" /><keypoint name="R_B_Elbow" visible="0" x="0.00" y="0.00" z="0.00" /><keypoint name="L_F_Knee" visible="0" x="0.00" y="0.00" z="0.00" /><keypoint name="R_F_Knee" visible="0" x="0.00" y="0.00" z="0.00" /><keypoint name="L_B_Knee" visible="0" x="0.00" y="0.00" z="0.00" /><keypoint name="R_B_Knee" visible="0" x="0.00" y="0.00" z="0.00" /></keypoints>
	<polylinesegments>
		<segment name="foreground" x="256.33 228.74 197.70 186.49 185.63 408.08 409.81 432.23 437.40 448.61 443.44 434.81 438.26 451.20 437.40 461.54 457.23 421.88 371.87 364.97 355.49 345.14 343.42 296.86 283.92 " y="202.65 210.40 232.81 264.69 328.46 332.77 304.33 302.61 286.24 269.86 239.70 204.37 156.98 112.17 95.80 62.19 51.85 76.84 63.91 46.68 42.37 63.05 88.90 182.83 202.65 " />
	</polylinesegments>
</annotation>