<annotation>
	<image>2011_001549</image>
	<voc_id>1</voc_id>
	<category>sheep</category>
	<visible_bounds height="176.00" width="214.00" xmin="180.00" ymin="90.00" />
	<keypoints>
		<keypoint name="L_Eye" visible="1" x="210.84" y="118.04" z="0.00" />
		<keypoint name="Nose" visible="1" x="188.08" y="130.93" z="0.00" />
		<keypoint name="L_EarBase" visible="1" x="219.49" y="103.42" z="0.00" />
		<keypoint name="R_EarBase" visible="1" x="188.83" y="98.22" z="0.00" />
		<keypoint name="Throat" visible="1" x="220.73" y="139.35" z="0.00" />
		<keypoint name="Withers" visible="1" x="249.16" y="113.33" z="0.00" />
		<keypoint name="TailBase" visible="1" x="379.73" y="115.81" z="0.00" />
		<keypoint name="L_F_Elbow" visible="1" x="253.37" y="175.03" z="0.00" />
		<keypoint name="L_B_Elbow" visible="1" x="374.05" y="165.62" z="0.00" />
		<keypoint name="L_F_Paw" visible="1" x="241.99" y="256.80" z="0.00" />
		<keypoint name="L_B_Paw" visible="1" x="386.66" y="242.18" z="0.00" />
		<keypoint name="R_B_Paw" visible="1" x="366.13" y="237.22" z="0.00" />
	<keypoint name="R_Eye" visible="0" x="0.00" y="0.00" z="0.00" /><keypoint name="R_F_Elbow" visible="0" x="0.00" y="0.00" z="0.00" /><keypoint name="R_F_Paw" visible="0" x="0.00" y="0.00" z="0.00" /><keypoint name="R_B_Elbow" visible="0" x="0.00" y="0.00" z="0.00" /><keypoint name="L_F_Knee" visible="0" x="0.00" y="0.00" z="0.00" /><keypoint name="R_F_Knee" visible="0" x="0.00" y="0.00" z="0.00" /><keypoint name="L_B_Knee" visible="1" x="383.75" y="203.90625" z="0.00" /><keypoint name="R_B_Knee" visible="1" x="366.25" y="206.25" z="0.00" /></keypoints>
	<polylinesegments>
		<segment name="foreground" x="181.16 185.12 188.58 187.59 188.58 184.62 179.68 187.10 196.49 205.89 209.85 221.72 233.59 240.51 256.34 282.05 313.71 340.41 359.21 377.01 388.88 391.85 388.39 385.92 387.89 384.93 388.88 390.37 394.32 391.85 384.43 380.97 383.44 381.96 374.05 371.57 374.05 375.03 369.59 366.63 360.69 365.64 364.15 357.23 347.34 332.01 317.17 299.86 289.47 281.56 283.04 292.44 296.89 288.98 283.04 282.05 273.15 273.15 261.78 249.41 241.99 231.61 221.22 208.36 201.44 190.56 181.16 " y="131.42 123.49 118.54 112.10 106.64 103.18 92.27 94.26 101.19 95.25 90.29 90.29 96.73 107.64 115.07 111.60 104.66 101.69 103.18 111.10 126.96 141.83 159.67 172.55 180.98 191.88 203.77 218.64 232.52 248.37 248.37 246.39 234.50 218.14 201.30 211.70 224.59 234.99 240.94 243.42 243.42 232.52 208.73 200.30 197.33 202.78 209.72 208.23 211.21 209.72 201.30 198.82 196.84 194.36 190.89 183.95 178.50 170.57 164.13 160.16 153.23 147.28 142.32 137.37 137.37 136.87 135.88 " />
	</polylinesegments>
</annotation>