<annotation>
	<image>2008_004354</image>
	<voc_id>1</voc_id>
	<category>horse</category>
	<visible_bounds height="269.00" width="415.00" xmin="14.00" ymin="115.00" />
	<keypoints>
		<keypoint name="R_Eye" visible="1" x="413.32" y="163.60" z="0.00" />
		<keypoint name="Nose" visible="1" x="416.20" y="205.12" z="0.00" />
		<keypoint name="L_EarBase" visible="1" x="411.40" y="125.68" z="0.00" />
		<keypoint name="R_EarBase" visible="1" x="417.48" y="139.60" z="0.00" />
		<keypoint name="Throat" visible="1" x="360.25" y="195.92" z="0.00" />
		<keypoint name="Withers" visible="1" x="311.34" y="165.20" z="0.00" />
		<keypoint name="TailBase" visible="1" x="137.82" y="193.84" z="0.00" />
		<keypoint name="R_F_Elbow" visible="1" x="322.53" y="257.68" z="0.00" />
		<keypoint name="R_B_Elbow" visible="1" x="184.09" y="255.12" z="0.00" />
		<keypoint name="L_F_Paw" visible="1" x="403.25" y="371.44" z="0.00" />
		<keypoint name="R_F_Paw" visible="1" x="342.83" y="347.20" z="0.00" />
		<keypoint name="L_B_Paw" visible="1" x="143.09" y="373.60" z="0.00" />
		<keypoint name="R_B_Paw" visible="1" x="258.91" y="368.80" z="0.00" />
	<keypoint name="L_Eye" visible="0" x="0.00" y="0.00" z="0.00" /><keypoint name="L_F_Elbow" visible="0" x="0.00" y="0.00" z="0.00" /><keypoint name="L_B_Elbow" visible="0" x="0.00" y="0.00" z="0.00" /><keypoint name="L_F_Knee" visible="0" x="0.00" y="0.00" z="0.00" /><keypoint name="R_F_Knee" visible="1" x="363.125" y="293.6125183105469" z="0.00" /><keypoint name="L_B_Knee" visible="1" x="123.75" y="313.84375" z="0.00" /><keypoint name="R_B_Knee" visible="1" x="201.25" y="312.2875061035156" z="0.00" /></keypoints>
	<polylinesegments>
		<segment name="foreground" x="316.45 360.57 392.22 405.65 413.32 419.08 425.79 422.91 423.87 426.75 412.36 397.02 379.75 378.79 361.53 364.41 359.61 370.16 378.79 375.92 397.98 418.12 410.44 395.10 376.88 369.20 356.73 343.31 329.88 333.72 353.86 359.61 344.27 310.70 284.80 204.24 206.15 215.75 240.68 260.82 269.46 264.66 251.23 236.85 232.05 193.69 182.18 170.67 162.99 143.81 134.22 138.06 152.44 137.10 120.79 117.92 114.08 133.26 129.43 127.51 127.51 110.24 97.77 77.63 43.11 22.00 15.29 32.56 53.66 83.39 106.41 135.18 165.87 201.36 230.13 " y="154.00 130.00 124.24 125.20 115.60 124.24 122.32 141.52 174.16 207.76 216.40 214.48 183.76 175.12 209.68 245.20 258.64 284.56 300.88 311.44 353.68 369.04 375.76 380.56 357.52 330.64 349.84 360.40 349.84 337.36 322.96 298.00 291.28 274.00 272.08 264.40 288.40 315.28 336.40 350.80 367.12 373.84 376.72 365.20 352.72 323.92 311.44 267.28 295.12 310.48 332.56 362.32 374.80 379.60 373.84 319.12 309.52 279.76 252.88 211.60 195.28 207.76 254.80 287.44 303.76 265.36 251.92 244.24 264.40 206.80 188.56 183.76 176.08 173.20 172.24 " />
	</polylinesegments>
</annotation>