<annotation>
	<image>2010_004804</image>
	<voc_id>1</voc_id>
	<category>dog</category>
	<visible_bounds height="289.00" width="374.00" xmin="126.00" ymin="86.00" />
	<keypoints>
		<keypoint name="L_Eye" visible="1" x="209.28" y="199.33" z="0.00" />
		<keypoint name="Nose" visible="1" x="143.87" y="242.33" z="0.00" />
		<keypoint name="L_EarBase" visible="1" x="427.09" y="128.35" z="0.00" />
		<keypoint name="Throat" visible="1" x="324.24" y="366.42" z="0.00" />
		<keypoint name="Withers" visible="1" x="494.08" y="269.89" z="0.00" />
	<keypoint name="R_Eye" visible="0" x="0.00" y="0.00" z="0.00" /><keypoint name="R_EarBase" visible="0" x="0.00" y="0.00" z="0.00" /><keypoint name="L_F_Elbow" visible="0" x="0.00" y="0.00" z="0.00" /><keypoint name="R_F_Elbow" visible="0" x="0.00" y="0.00" z="0.00" /><keypoint name="L_F_Paw" visible="0" x="0.00" y="0.00" z="0.00" /><keypoint name="R_F_Paw" visible="0" x="0.00" y="0.00" z="0.00" /><keypoint name="TailBase" visible="0" x="0.00" y="0.00" z="0.00" /><keypoint name="L_B_Paw" visible="0" x="0.00" y="0.00" z="0.00" /><keypoint name="R_B_Paw" visible="0" x="0.00" y="0.00" z="0.00" /><keypoint name="L_B_Elbow" visible="0" x="0.00" y="0.00" z="0.00" /><keypoint name="R_B_Elbow" visible="0" x="0.00" y="0.00" z="0.00" /><keypoint name="L_F_Knee" visible="0" x="0.00" y="0.00" z="0.00" /><keypoint name="R_F_Knee" visible="0" x="0.00" y="0.00" z="0.00" /><keypoint name="L_B_Knee" visible="0" x="0.00" y="0.00" z="0.00" /><keypoint name="R_B_Knee" visible="0" x="0.00" y="0.00" z="0.00" /></keypoints>
	<polylinesegments>
		<segment name="foreground" x="250.77 202.36 194.58 160.87 158.28 148.77 128.89 128.03 128.03 133.21 160.87 194.58 224.84 248.17 239.53 498.84 503.16 478.09 460.80 444.38 475.50 497.97 499.70 460.80 395.11 356.22 351.90 " y="91.12 126.61 132.67 162.11 199.33 219.25 235.69 260.80 288.50 311.01 342.18 357.76 357.76 362.95 371.61 374.21 272.05 226.17 186.35 166.44 169.90 144.79 98.91 88.52 91.12 91.12 87.66 " />
	</polylinesegments>
</annotation>